a11y_pygments/__init__.py
a11y_pygments/a11y_dark/__init__.py
a11y_pygments/a11y_dark/style.py
a11y_pygments/a11y_high_contrast_dark/__init__.py
a11y_pygments/a11y_high_contrast_dark/style.py
a11y_pygments/a11y_high_contrast_light/__init__.py
a11y_pygments/a11y_high_contrast_light/style.py
a11y_pygments/a11y_light/__init__.py
a11y_pygments/a11y_light/style.py
a11y_pygments/blinds_dark/__init__.py
a11y_pygments/blinds_dark/style.py
a11y_pygments/blinds_light/__init__.py
a11y_pygments/blinds_light/style.py
a11y_pygments/github_dark/__init__.py
a11y_pygments/github_dark/style.py
a11y_pygments/github_dark_colorblind/__init__.py
a11y_pygments/github_dark_colorblind/style.py
a11y_pygments/github_dark_high_contrast/__init__.py
a11y_pygments/github_dark_high_contrast/style.py
a11y_pygments/github_light/__init__.py
a11y_pygments/github_light/style.py
a11y_pygments/github_light_colorblind/__init__.py
a11y_pygments/github_light_colorblind/style.py
a11y_pygments/github_light_high_contrast/__init__.py
a11y_pygments/github_light_high_contrast/style.py
a11y_pygments/gotthard_dark/__init__.py
a11y_pygments/gotthard_dark/style.py
a11y_pygments/gotthard_light/__init__.py
a11y_pygments/gotthard_light/style.py
a11y_pygments/greative/__init__.py
a11y_pygments/greative/style.py
a11y_pygments/pitaya_smoothie/__init__.py
a11y_pygments/pitaya_smoothie/style.py
a11y_pygments/utils/__init__.py
a11y_pygments/utils/utils.py
accessible_pygments-0.0.4.dist-info/LICENSE
accessible_pygments-0.0.4.dist-info/METADATA
accessible_pygments-0.0.4.dist-info/WHEEL
accessible_pygments-0.0.4.dist-info/entry_points.txt
accessible_pygments-0.0.4.dist-info/top_level.txt
accessible_pygments-0.0.4.dist-info/RECORD
