Metadata-Version: 2.1
Name: accessible-pygments
Version: 0.0.4
Summary: A collection of accessible pygments styles
Home-page: https://github.com/Quansight-Labs/accessible-pygments
Author: Stephannie Jimenez Gacha
Author-email: steff456@hotmail.com
License: BSD
Keywords: pygments style accessible a11
Platform: UNKNOWN
Classifier: Intended Audience :: Developers
Classifier: License :: OSI Approved :: BSD License
Classifier: Operating System :: OS Independent
Classifier: Programming Language :: Python
Classifier: Programming Language :: Python :: 2
Classifier: Programming Language :: Python :: 3
Classifier: Topic :: Software Development :: Libraries :: Python Modules
License-File: LICENSE
